{
  "id": "ts27",
  "what": "accessibility tests",
  "strict": true,
  "timeLimit": 330,
  "acts": [
    {
      "type": "placeholder",
      "which": "main",
      "launch": "webkit"
    },
    {
      "type": "tenonRequest",
      "id": "a",
      "withNewContent": false,
      "what": "Tenon API version 2 test request, with page content"
    },
    {
      "type": "test",
      "which": "testaro",
      "what": "Testaro motion test (requires webkit)",
      "withItems": true,
      "rules": ["y", "motion"]
    },
    {
      "type": "placeholder",
      "which": "main",
      "launch": "chromium"
    },
    {
      "type": "test",
      "which": "alfa"
    },
    {
      "type": "test",
      "which": "axe",
      "detailLevel": 2
    },
    {
      "type": "test",
      "which": "continuum"
    },
    {
      "type": "test",
      "which": "htmlcs"
    },
    {
      "type": "test",
      "which": "ibm",
      "withItems": true,
      "withNewContent": false
    },
    {
      "type": "test",
      "which": "nuVal"
    },
    {
      "type": "test",
      "which": "qualWeb",
      "withNewContent": false
    },
    {
      "type": "test",
      "which": "tenon",
      "id": "a"
    },
    {
      "type": "test",
      "which": "testaro",
      "withItems": true,
      "rules": ["n", "motion"]
    },
    {
      "type": "test",
      "which": "wave",
      "reportType": 4
    }
  ]
}
